<?xml version="1.0" encoding="ISO-8859-1"?>
<message_catalog package_key="accounts-ledger" package_version="0.1d" locale="de_DE" charset="ISO-8859-1">


<msg key="DE_0000">ANLAGEVERMÖGEN</msg>
<msg key="DE_0100">Konzessionen &amp; Lizenzen</msg>
<msg key="DE_0135">EDV-Programme</msg>
<msg key="DE_0440">Maschinen</msg>
<msg key="DE_0500">Betriebsausstattung</msg>
<msg key="DE_0520">PKW</msg>
<msg key="DE_0650">Büroeinrichtung</msg>
<msg key="DE_0670">GWG</msg>
<msg key="DE_1100">WARENBESTAND</msg>
<msg key="DE_1140">Warenbestand</msg>
<msg key="DE_1200">FORDERUNGEN</msg>
<msg key="DE_1201">Geleistete Anzahlungen</msg>
<msg key="DE_1210">Forderungen ohne Kontokorrent</msg>
<msg key="DE_1300">Sonstige Forderungen</msg>
<msg key="DE_1400">Anrechenbare Vorsteuer</msg>
<msg key="DE_1401">Anrechenbare Vorsteuer 7%</msg>
<msg key="DE_1402">Vorsteuer ig Erwerb</msg>
<msg key="DE_1403">Vorsteuer ig Erwerb 16%</msg>
<msg key="DE_1405">Anrechenbare Vorsteuer 16%</msg>
<msg key="DE_1406">Anrechenbare Vorsteuer 15%</msg>
<msg key="DE_1433">bezahlte Einfuhrumsatzsteuer</msg>
<msg key="DE_1370">Ungeklärte Posten</msg>
<msg key="DE_1600">LIQUIDE MITTEL</msg>
<msg key="DE_1601">Kasse</msg>
<msg key="DE_1700">Postgiro</msg>
<msg key="DE_1800">Bank</msg>
<msg key="DE_1810">Bank USD</msg>
<msg key="DE_1820">Kreditkarten</msg>
<msg key="DE_1890">Geldtransit</msg>
<msg key="DE_1900">Aktive Rechnungsabgrenzung</msg>
<msg key="DE_2000">EIGENKAPITAL</msg>
<msg key="DE_2001">Eigenkapital</msg>
<msg key="DE_2100">Privatentnahmen</msg>
<msg key="DE_2150">Privatsteuern</msg>
<msg key="DE_2180">Privateinlagen</msg>
<msg key="DE_2200">Sonderausgaben beschr.abzugsf.</msg>
<msg key="DE_2900">Gezeichnetes Kapital</msg>
<msg key="DE_2910">Ausstehende Einlagen</msg>
<msg key="DE_2970">Gewinnvortrag vor Verwendung</msg>
<msg key="DE_2978">Verlustvortrag vor Verwendung</msg>
<msg key="DE_3000">RÜCKSTELLUNGEN</msg>
<msg key="DE_3030">Gewerbesteuerrückstellung</msg>
<msg key="DE_3070">Sonstige Rückstellungen</msg>
<msg key="DE_3095">Rückstellung für Abschlusskosten</msg>
<msg key="DE_3100">FREMDKAPITAL LANGFRISTIG</msg>
<msg key="DE_3160">Bankdarlehen</msg>
<msg key="DE_3200">FREMDKAPITAL KURZFRISTIG</msg>
<msg key="DE_3280">Erhaltene Anzahlungen</msg>
<msg key="DE_3310">Kreditoren ohne Kontokorrent</msg>
<msg key="DE_3500">Sonstige Verbindlichkeiten</msg>
<msg key="DE_3560">Darlehen</msg>
<msg key="DE_3700">Verbindl. Betr.steuern u.Abgaben</msg>
<msg key="DE_3720">Verbindlichkeiten Löhne und Gehälter</msg>
<msg key="DE_3730">Verbindlichkeiten Lohnsteuer</msg>
<msg key="DE_3740">Verbindlichkeiten Sozialversicherung</msg>
<msg key="DE_3800">Umsatzsteuer</msg>
<msg key="DE_3801">Umsatzsteuer 7%</msg>
<msg key="DE_3802">Umsatzsteuer ig. Erwerb</msg>
<msg key="DE_3803">Umsatzsteuer ig. Erwerb 16%</msg>
<msg key="DE_3805">Umsatzsteuer 16%</msg>
<msg key="DE_3806">Umsatzsteuer 15%</msg>
<msg key="DE_3815">Umsatzsteuer nicht fällig 16%</msg>
<msg key="DE_3816">Umsatzsteuer nicht fällig 15%</msg>
<msg key="DE_3820">Umsatzsteuer-Vorauszahlungen</msg>
<msg key="DE_3841">Umsatzsteuer Vorjahr</msg>
<msg key="DE_3900">Aktive Rechnungsabgrenzung</msg>
<msg key="DE_5100">WARENEINGANG</msg>
<msg key="DE_5200">Wareneingang ohne Vorsteuer</msg>
<msg key="DE_5300">Wareneingang 7%</msg>
<msg key="DE_5400">Wareneingang 15%</msg>
<msg key="DE_5420">ig.Erwerb 7% VoSt. und 7% USt.</msg>
<msg key="DE_5425">ig.Erwerb 15% VoSt. und 15% USt.</msg>
<msg key="DE_5731">Erhaltene Skonti 7% Vorsteuer</msg>
<msg key="DE_5736">Erhaltene Skonti 15% Vorsteuer</msg>
<msg key="DE_5800">Anschaffungsnebenkosten</msg>
<msg key="DE_5900">Fremdarbeiten</msg>
<msg key="DE_6000">PERSONALKOSTEN</msg>
<msg key="DE_6001">Personalkosten</msg>
<msg key="DE_6010">Löhne</msg>
<msg key="DE_6020">Gehälter</msg>
<msg key="DE_6030">Aushilfslöhne</msg>
<msg key="DE_6040">Lohnsteuer Aushilfen</msg>
<msg key="DE_6080">Vermögenswirksame Leistungen</msg>
<msg key="DE_6090">Fahrtkostenerst.Whg./Arbeitsstätte</msg>
<msg key="DE_6110">Sozialversicherung</msg>
<msg key="DE_6120">Berufsgenossenschaft</msg>
<msg key="DE_6130">Freiw. Soz. Aufw. LSt- u. Soz.Vers.frei</msg>
<msg key="DE_6300">RAUMKOSTEN</msg>
<msg key="DE_6310">Miete</msg>
<msg key="DE_6315">Pacht</msg>
<msg key="DE_6320">Heizung</msg>
<msg key="DE_6325">Gas Strom Wasser</msg>
<msg key="DE_6330">Reinigung</msg>
<msg key="DE_6335">Instandhaltung betriebliche Räume</msg>
<msg key="DE_6345">Sonstige Raumkosten</msg>
<msg key="DE_6400">SONSTIGE KOSTEN</msg>
<msg key="DE_6402">Abschreibungen</msg>
<msg key="DE_6403">Kaufleasing</msg>
<msg key="DE_6404">Sofortabschreibung GWG</msg>
<msg key="DE_6405">Sonstige Kosten</msg>
<msg key="DE_6410">Versicherung</msg>
<msg key="DE_6420">Beiträge und Gebühren</msg>
<msg key="DE_6430">Sonstige Abgaben</msg>
<msg key="DE_6470">Rep. und Instandhaltung BGA</msg>
<msg key="DE_6520">Kfz-Versicherung</msg>
<msg key="DE_6530">Lfd. Kfz-Kosten</msg>
<msg key="DE_6540">Kfz-Reparaturen</msg>
<msg key="DE_6560">Fremdfahrzeuge</msg>
<msg key="DE_6570">Sonstige Kfz-Kosten</msg>
<msg key="DE_6600">Werbung</msg>
<msg key="DE_6610">Kundengeschenke bis DM 75.</msg>
<msg key="DE_6620">Kundengeschenke über DM 75.-</msg>
<msg key="DE_6630">Repräsentationkosten</msg>
<msg key="DE_6640">Bewirtungskosten</msg>
<msg key="DE_6644">Nicht abzugsf.Bewirtungskosten</msg>
<msg key="DE_6650">Reisekosten Arbeitnehmer</msg>
<msg key="DE_6660">Reisekosten Arbeitnehmer 12.3%</msg>
<msg key="DE_6665">Reisekosten Arbeitnehmer 9.8%</msg>
<msg key="DE_6670">Reisekosten Unternehmer</msg>
<msg key="DE_6680">Reisekosten Unternehmer 12.3%</msg>
<msg key="DE_6685">Reisekosten Unternehmer 9.8%</msg>
<msg key="DE_6688">Reisekosten Unternehmer 5.7%</msg>
<msg key="DE_6690">Km-Geld-Erstattung 8.2%</msg>
<msg key="DE_6710">Verpackungsmaterial</msg>
<msg key="DE_6740">Ausgangsfrachten</msg>
<msg key="DE_6780">Fremdarbeiten</msg>
<msg key="DE_6800">Porto</msg>
<msg key="DE_6805">Telefon</msg>
<msg key="DE_6815">Bürobedarf</msg>
<msg key="DE_6820">Zeitschriften &amp; Bücher</msg>
<msg key="DE_6825">Rechts- und Beratungskosten</msg>
<msg key="DE_6835">Mieten für Einrichtungen</msg>
<msg key="DE_6840">Mietleasing</msg>
<msg key="DE_6845">Werkzeuge und Kleingeräte</msg>
<msg key="DE_6850">Betriebsbedarf</msg>
<msg key="DE_6852">Gastättenbedarf</msg>
<msg key="DE_6855">Nebenkosten des Geldverkehrs</msg>
<msg key="DE_6880">Aufwendungen aus Kursdifferenzen</msg>
<msg key="DE_6885">Erlöse aus Anlageverk.(Buchverlust)</msg>
<msg key="DE_7610">Gewerbesteuer</msg>
<msg key="DE_7685">Kfz-Steuer</msg>
<msg key="DE_8100">ERTRÄGE</msg>
<msg key="DE_8120">Steuerfreie Umsätze 4 Nr. 1a UStG.</msg>
<msg key="DE_8125">Steuerfreie ig. Lieferungen 1b UStG.</msg>
<msg key="DE_8200">Erlöse ohne Umsatzsteuer</msg>
<msg key="DE_8300">Erlöse 7% Umsatzsteuer</msg>
<msg key="DE_8400">Erlöse 15% Umsatzsteuer</msg>
<msg key="DE_8500">Provisionserlöse</msg>
<msg key="DE_8630">Entnahme sonstg. Leistungen 7% USt.</msg>
<msg key="DE_8640">Entnahme sonstg. Leistungen 15% USt.</msg>
<msg key="DE_8731">Gew. Skonti 7% USt.</msg>
<msg key="DE_8736">Gew. Skonti 15% USt.</msg>
<msg key="DE_8840">Erträge aus Kursdifferenzen</msg>
<msg key="DE_8845">Erlöse aus Anlageverk. (Buchgewinn)</msg>
<msg key="DE_8900">Erträge aus Abgang von Anlageverm.</msg>
<msg key="DE_9300">NEUTRALE AUFWENDUNGEN</msg>
<msg key="DE_9310">Zinsen kurzfr. Verbindlichkeiten</msg>
<msg key="DE_9320">Zinsen langfr. Verbindlichkeiten</msg>
<msg key="DE_9500">Ausserordentl.Aufwendungen</msg>
<msg key="DE_9600">NEUTRALE ERTRÄGE</msg>
<msg key="DE_9610">Guthabenzinsen</msg>
<msg key="DE_9700">Ausserordentl.Erträge</msg>
<?xml version="1.0" encoding="ISO-8859-1"?>
<message_catalog package_key="accounts-ledger" package_version="0.1d" locale="de_DE" charset="ISO-8859-1">


<msg key="DE_DATEV_0002700">EDV-Software</msg>
<msg key="DE_DATEV_0010000">Fabrikbauten</msg>
<msg key="DE_DATEV_0011000">Garagen</msg>
<msg key="DE_DATEV_0011100">Außenanlagen</msg>
<msg key="DE_DATEV_0011200">Hof-und Wegebefestigung</msg>
<msg key="DE_DATEV_0011500">Andere Bauten</msg>
<msg key="DE_DATEV_0016500">Geschäftsbauten</msg>
<msg key="DE_DATEV_0008500">Grundstückswert eige.bebau.Grundst.</msg>
<msg key="DE_DATEV_0009000">Geschäftsbauten</msg>
<msg key="DE_DATEV_0016000">Bauten auf fremden Grundstücken</msg>
<msg key="DE_DATEV_0017000">Fabrikbauten</msg>
<msg key="DE_DATEV_0017500">Garagen</msg>
<msg key="DE_DATEV_0017600">Außenanlage</msg>
<msg key="DE_DATEV_0020000">Techn.Anlagen und Maschinen</msg>
<msg key="DE_DATEV_0021000">Maschinen</msg>
<msg key="DE_DATEV_0022000">Maschinengebundene Werkzeuge</msg>
<msg key="DE_DATEV_0024000">Maschinelle Anlagen</msg>
<msg key="DE_DATEV_0028000">Betriebsvorrichtung</msg>
<msg key="DE_DATEV_0030000">Andere Anlagen,Betrieb-und Geschäftsaus</msg>
<msg key="DE_DATEV_0031000">Andere Anlagen</msg>
<msg key="DE_DATEV_0032000">PKW</msg>
<msg key="DE_DATEV_0035000">LKW</msg>
<msg key="DE_DATEV_0040000">Betriebsausstattung</msg>
<msg key="DE_DATEV_0041000">Geschäftsausstattung</msg>
<msg key="DE_DATEV_0042000">Büroeinrichtung</msg>
<msg key="DE_DATEV_0043000">Ladeneinrichtung</msg>
<msg key="DE_DATEV_0048000">Geringwertige Wirtschaftsg.b.410EUR</msg>
<msg key="DE_DATEV_0049000">Sons.Betriebs- Geschäftsausstattung</msg>
<msg key="DE_DATEV_0050400">Ant.a.herr.o.m.Mehrh.bet.Ges.schaft</msg>
<msg key="DE_DATEV_0051300">Typisch stille Beteiligungen</msg>
<msg key="DE_DATEV_0063100">- Restlaufzeit bis 1 Jahr</msg>
<msg key="DE_DATEV_0051600">Atypische stille Beteiligungen</msg>
<msg key="DE_DATEV_0064000">- Restlaufzeit 1 bis 5 Jahre</msg>
<msg key="DE_DATEV_0065000">- Restlaufzeit größer als 5 Jahre</msg>
<msg key="DE_DATEV_0099600">Pauschalwertb.m.Restlaufzeit v. 1J.</msg>
<msg key="DE_DATEV_0140000">Ford. a.Lieferungen und Leistungen</msg>
<msg key="DE_DATEV_0080000">Gezeichnetes Kapital</msg>
<msg key="DE_DATEV_0150000">Sonstige Vermögensgegenstände</msg>
<msg key="DE_DATEV_0153000">Forderungen gegen Personal</msg>
<msg key="DE_DATEV_0154500">Umsatzsteuerforderungen</msg>
<msg key="DE_DATEV_0100000">Kasse</msg>
<msg key="DE_DATEV_0120000">Bank</msg>
<msg key="DE_DATEV_0096300">Körperschaftssteuerrückstellung</msg>
<msg key="DE_DATEV_0095500">Steuerrückstellung</msg>
<msg key="DE_DATEV_0095700">Gewerbesteuerrückstellung</msg>
<msg key="DE_DATEV_0080100">Ausst.Einl.a.d.gezeichnete Kapital</msg>
<msg key="DE_DATEV_0084000">Kapitalrücklage</msg>
<msg key="DE_DATEV_0086000">Gewinnvortrag vor Verwendung</msg>
<msg key="DE_DATEV_0086900">Vortrag auf neue Rechnungen</msg>
<msg key="DE_DATEV_0000500">Sachanlagen</msg>
<msg key="DE_DATEV_0050000">Finanzanlagen</msg>
<msg key="DE_DATEV_0051000">Beteiligungen</msg>
<msg key="DE_DATEV_0063000">Verbindl.gegenüber Kreditinstituten</msg>
<msg key="DE_DATEV_0060000">Verbindlichkeiten</msg>
<msg key="DE_DATEV_0086800">Verlustvortrag vor Verwendung</msg>
<msg key="DE_DATEV_0097000">Sonstige Rückstellungen</msg>
<msg key="DE_DATEV_0097400">Rückstellungen für Gewährleistungen</msg>
<msg key="DE_DATEV_0097700">Rücks.f.Abschluß-u.Prüfungskosten</msg>
<msg key="DE_DATEV_0097800">Aufwandsrückstellungen</msg>
<msg key="DE_DATEV_0098000">Aktive Rechnungsabgrenzung</msg>
<msg key="DE_DATEV_0099000">Passive Rechnungsabgrenzung</msg>
<msg key="DE_DATEV_0099200">Wertberichtigungen</msg>
<msg key="DE_DATEV_0099800">Einzelwertber.m.Restlaufzeit v.1 J.</msg>
<msg key="DE_DATEV_0146000">Zweifelhafte Forderungen</msg>
<msg key="DE_DATEV_0151000">Geleistete Anzahlung auf Vorräte</msg>
<msg key="DE_DATEV_0151100">Geleistete Anzahlungen 7%</msg>
<msg key="DE_DATEV_0151700">Geleistete Anzahlung 16%</msg>
<msg key="DE_DATEV_0152500">Kautionen</msg>
<msg key="DE_DATEV_0154000">Steuerüberzahlungen</msg>
<msg key="DE_DATEV_0157000">Abziehbare Vorsteuer</msg>
<msg key="DE_DATEV_0160000">Verbindlichkeiten aus Lief.u.Leist.</msg>
<msg key="DE_DATEV_0174100">Verbindl.a.Lohn-und Kirchensteuer</msg>
<msg key="DE_DATEV_0178000">Umsatzsteuer-Vorauszahlungen</msg>
<msg key="DE_DATEV_0178100">Umsatzsteuer-Vorauszahlung 1/11</msg>
<msg key="DE_DATEV_0178900">Umsatzsteuer laufendes Jahr</msg>
<msg key="DE_DATEV_0179000">Umsatzsteuer Vorjahr</msg>
<msg key="DE_DATEV_0179100">Umsatzsteuer frühere Jahre</msg>
<msg key="DE_DATEV_0180000">Privatentnahme allgemein</msg>
<msg key="DE_DATEV_0189000">Privateinlagen</msg>
<msg key="DE_DATEV_0210000">Zinsen und ähnl.Aufwendungen</msg>
<msg key="DE_DATEV_0211000">Zinsaufwendung f.kurzf.Verbindlichk</msg>
<msg key="DE_DATEV_0212000">Zinsaufwendung f.langf.Verbindlichk</msg>
<msg key="DE_DATEV_0221000">Kapitalertragssteuer</msg>
<msg key="DE_DATEV_0231000">Anlagenabgänge - bei Buchverlust</msg>
<msg key="DE_DATEV_0231500">Anlagenabgänge-Buchgewinn</msg>
<msg key="DE_DATEV_0237500">Grundsteuer</msg>
<msg key="DE_DATEV_0245000">Einstell.i.d.Pauschalwertbe.z.Forde</msg>
<msg key="DE_DATEV_0245100">Einstell.i.d.Einzelwertb.z.Forderun</msg>
<msg key="DE_DATEV_0250000">Außerordentliche Erträge</msg>
<msg key="DE_DATEV_0251000">Betriebsfremde Erträge n.außerorden</msg>
<msg key="DE_DATEV_0252000">Periodenfremde Erträge nicht außero</msg>
<msg key="DE_DATEV_0270000">Sonstige Erträge</msg>
<msg key="DE_DATEV_0272000">Ertr.a.d.Abgang v.Gegens.d.Anlageve</msg>
<msg key="DE_DATEV_0272500">Ertr.a.d.Abg.v.Gegenst.d.Umlaufverm</msg>
<msg key="DE_DATEV_0273000">Ertr.a.Herab.d.Pauschal.z.Forderung</msg>
<msg key="DE_DATEV_0273100">Ertr.a.Herab.d.Einzelw.z.Forderunge</msg>
<msg key="DE_DATEV_0273200">Ertr. aus abgeschriebenen Forderung</msg>
<msg key="DE_DATEV_0274200">Versicherungsentschädigungen</msg>
<msg key="DE_DATEV_0286000">Gewinnvortrag nach Verwendung</msg>
<msg key="DE_DATEV_0286800">Verlustvortrag nach Verwendung</msg>
<msg key="DE_DATEV_0286900">Vortrag auf neue Rechnungen</msg>
<msg key="DE_DATEV_0375000">Erhaltene Boni 7% Vorsteuer</msg>
<msg key="DE_DATEV_0376000">Erhaltene Boni 16% Vorsteuer</msg>
<msg key="DE_DATEV_0380000">Anschaffungsnebenkosten</msg>
<msg key="DE_DATEV_0383000">Leergut</msg>
<msg key="DE_DATEV_0385000">Zölle und Einfuhrabgaben</msg>
<msg key="DE_DATEV_0396000">Bestandsver.Roh-,Hilfs-.Betriebs.</msg>
<msg key="DE_DATEV_0397000">Bestand Roh-,Hilfs-,u.Betriebsstoff</msg>
<msg key="DE_DATEV_0398000">Bestand Waren</msg>
<msg key="DE_DATEV_0399000">Verrechnete Stoffkosten</msg>
<msg key="DE_DATEV_0400000">Material-und Stoffverbrauch</msg>
<msg key="DE_DATEV_0410000">Löhne und Gehälter</msg>
<msg key="DE_DATEV_0412500">Ehegattengehalt</msg>
<msg key="DE_DATEV_0340000">Wareneingang 16% Vorsteuer</msg>
<msg key="DE_DATEV_0342000">Innergemein.Erwerb 7% VorSt u. Ust</msg>
<msg key="DE_DATEV_0342500">Innergem.Erwerb 16% VorSt u. Ust</msg>
<msg key="DE_DATEV_0373100">Erhaltene Skonti 7% Vorsteuer</msg>
<msg key="DE_DATEV_0373500">Erhaltene Skonti 16% Vorsteuer</msg>
<msg key="DE_DATEV_0330000">Wareneingang 7% Vorsteuer</msg>
<msg key="DE_DATEV_0413000">Gesetzlich soziale Aufwendungen</msg>
<msg key="DE_DATEV_0413800">Beiträge zur Berufsgenossenschaftr</msg>
<msg key="DE_DATEV_0414500">Freiwillige sozi.Aufw.lohnsteuerfr.</msg>
<msg key="DE_DATEV_0414900">Pauschale Lohnsteuera.sons.Bezüge</msg>
<msg key="DE_DATEV_0416500">Aufwendung f.Altersversorgung</msg>
<msg key="DE_DATEV_0417000">Vermögenswirksame Leistungen</msg>
<msg key="DE_DATEV_0420000">Raumkosten</msg>
<msg key="DE_DATEV_0417500">Fahrtkostenerst.Wohnung/Arbeitsstät</msg>
<msg key="DE_DATEV_0419000">Aushilfslöhne</msg>
<msg key="DE_DATEV_0419900">Lohnsteuer für Aushilfe</msg>
<msg key="DE_DATEV_0159000">Durchlaufende Posten</msg>
<msg key="DE_DATEV_0422000">Pacht</msg>
<msg key="DE_DATEV_0423000">Heizung</msg>
<msg key="DE_DATEV_0424000">Gas,Strom, Wasser</msg>
<msg key="DE_DATEV_0425000">Reinigung</msg>
<msg key="DE_DATEV_0426000">Instandhaltung betrieb.Räume</msg>
<msg key="DE_DATEV_0428000">Sonstige Raumkosten</msg>
<msg key="DE_DATEV_0432000">Gewerbesteuer</msg>
<msg key="DE_DATEV_0434000">Sonstige Betriebssteuern</msg>
<msg key="DE_DATEV_0436000">Versicherungen</msg>
<msg key="DE_DATEV_0438000">Beiträge</msg>
<msg key="DE_DATEV_0439000">Sonstige Abgaben</msg>
<msg key="DE_DATEV_0450000">Fahrzugkosten</msg>
<msg key="DE_DATEV_0451000">Kfz-Steuer</msg>
<msg key="DE_DATEV_0452000">Kfz-Versicherungen</msg>
<msg key="DE_DATEV_0453000">Laufende Kfz-Betriebskosten</msg>
<msg key="DE_DATEV_0454000">Kfz-Reparaturen</msg>
<msg key="DE_DATEV_0455000">Garagenmiete</msg>
<msg key="DE_DATEV_0457000">Fremdfahrzeuge</msg>
<msg key="DE_DATEV_0458000">Sonstige Kfz-Kosten</msg>
<msg key="DE_DATEV_0461000">Werbekosten</msg>
<msg key="DE_DATEV_0463000">Geschenke bis 40 EUR</msg>
<msg key="DE_DATEV_0463500">Geschenke über 40 EUR</msg>
<msg key="DE_DATEV_0464000">Repräsentationskosten</msg>
<msg key="DE_DATEV_0465000">Bewirtungskosten</msg>
<msg key="DE_DATEV_0465400">Nicht abzugsfähige Bewirtungskosten</msg>
<msg key="DE_DATEV_0465500">Nicht abzugsfähige Betriebsausgaben</msg>
<msg key="DE_DATEV_0466300">Reisekosten Arbeitn.m.Vorsteuerabzu</msg>
<msg key="DE_DATEV_0466600">Reisekosten Arbeitn.Übernachtungsau</msg>
<msg key="DE_DATEV_0466800">Kilometerentgelderstattung Arbeitne</msg>
<msg key="DE_DATEV_0467400">Reisekosten Untern.Verpflegungsmehr</msg>
<msg key="DE_DATEV_0467600">Reisekosten Untern.Übernachtungsauf</msg>
<msg key="DE_DATEV_0467800">Kilometererstattungsgeld Unternehme</msg>
<msg key="DE_DATEV_0470000">Kosten der Warenabgabe</msg>
<msg key="DE_DATEV_0471000">Verpackungsmaterial</msg>
<msg key="DE_DATEV_0473000">Ausgangsfracht</msg>
<msg key="DE_DATEV_0475000">Transportversicherung</msg>
<msg key="DE_DATEV_0476000">Verkaufsprovision</msg>
<msg key="DE_DATEV_0478000">Fremdarbeiten</msg>
<msg key="DE_DATEV_0479000">Aufwand für Gewährleistungen</msg>
<msg key="DE_DATEV_0480900">Sonstige Reparaturen u.Instandhalt.</msg>
<msg key="DE_DATEV_0481000">Mietleasing</msg>
<msg key="DE_DATEV_0481500">Kaufleasing</msg>
<msg key="DE_DATEV_0482000">AfA a.Aufw.f.d.Inga.u.Erw.Geschäfts</msg>
<msg key="DE_DATEV_0482100">AfA a.Aufw.f.d.Währungsumst.a.Euro</msg>
<msg key="DE_DATEV_0483000">Abschreibungen auf Sachanlagen</msg>
<msg key="DE_DATEV_0485500">Sofortabschreibung GWG</msg>
<msg key="DE_DATEV_0491000">Porto</msg>
<msg key="DE_DATEV_0492000">Telefon</msg>
<msg key="DE_DATEV_0492500">Telefax</msg>
<msg key="DE_DATEV_0493000">Bürobedarf</msg>
<msg key="DE_DATEV_0494000">Zeitschriften, Bücher</msg>
<msg key="DE_DATEV_0494500">Fortbildungskosten</msg>
<msg key="DE_DATEV_0494600">Freiwillige Sozialleistungen</msg>
<msg key="DE_DATEV_0495000">Rechts- und Beratungskosten</msg>
<msg key="DE_DATEV_0495500">Buchführungskosten</msg>
<msg key="DE_DATEV_0495700">Abschluß- und Prüfungskosten</msg>
<msg key="DE_DATEV_0496000">Mieten für Einrichtungen</msg>
<msg key="DE_DATEV_0497000">Nebenkosten des Geldverkehrs</msg>
<msg key="DE_DATEV_0498000">Betriebsbedarf</msg>
<msg key="DE_DATEV_0498500">Werkzeuge und Kleingeräte</msg>
<msg key="DE_DATEV_0498600">Sonstige Aufwendungen (Ausbuchung)</msg>
<msg key="DE_DATEV_0700000">Unfertige Erzeu.unfert.Leistungen</msg>
<msg key="DE_DATEV_0136000">Geldtransit</msg>
<msg key="DE_DATEV_0705000">Unfertige Erzeugnisse</msg>
<msg key="DE_DATEV_0708000">Unfertige Leistungen</msg>
<msg key="DE_DATEV_0711000">Fertige Erzeugnisse (Bestand)</msg>
<msg key="DE_DATEV_0714000">Waren (Bestand)</msg>
<msg key="DE_DATEV_0873100">Gewährte Skonti 7% USt</msg>
<msg key="DE_DATEV_0873500">Gewährte Skonti 16% USt.</msg>
<msg key="DE_DATEV_0875000">Gewährte Boni 7% USt.</msg>
<msg key="DE_DATEV_0876000">Gewährte Boni 16% USt.</msg>
<msg key="DE_DATEV_0882000">Erlöse aus Anlageverkäufen 16%Ust</msg>
<msg key="DE_DATEV_0895500">Umsatzsteuervergütungen</msg>
<msg key="DE_DATEV_0890500">Entnahme v. Gegenst.o.USt.</msg>
<msg key="DE_DATEV_0900000">Saldenverträge,Sachkonten</msg>
<msg key="DE_DATEV_0900800">Saldenverträge,Debitoren</msg>
<msg key="DE_DATEV_0900900">Saldenverträge,Kreditoren</msg>
<msg key="DE_DATEV_0266000">Erträge aus Kursdifferenzen</msg>
<msg key="DE_DATEV_0215000">Aufwendungen aus Kursdifferenzen</msg>
<msg key="DE_DATEV_0850000">Provisionserlöse</msg>
<msg key="DE_DATEV_0157100">Abziebare Vorsteuer 7%</msg>
<msg key="DE_DATEV_0157500">Abziehbare Vorsteuer 16%</msg>
<msg key="DE_DATEV_0177100">Umsatzsteuer 7%</msg>
<msg key="DE_DATEV_0177500">Umsatzsteuer 16%</msg>
<msg key="DE_DATEV_0830000">Erlöse 7%USt</msg>
<msg key="DE_DATEV_0840000">Erlöse 16% USt.</msg>
<msg key="DE_DATEV_950">Rückstellungen</msg>
<?xml version="1.0" encoding="ISO-8859-1"?>
<message_catalog package_key="accounts-ledger" package_version="0.1d" locale="de_DE" charset="ISO-8859-1">


<msg key="DE_SKR03_420">Büroeinrichtung</msg>
<msg key="DE_SKR03_430">Ladeneinrichtung</msg>
<msg key="DE_SKR03_440">Werkzeuge</msg>
<msg key="DE_SKR03_450">Einbauten</msg>
<msg key="DE_SKR03_460">Gerüst- und Schalungsmaterial</msg>
<msg key="DE_SKR03_480">Geringwertige Wirtschaftsgüter bis DM 800,-</msg>
<msg key="DE_SKR03_490">Sonstige Betriebs- und Geschäftsausstattung</msg>
<msg key="DE_SKR03_650">Verb. gg. Kreditinstituten - Restlaufz. größer 5 Jahre</msg>
<msg key="DE_SKR03_1000">Kasse</msg>
<msg key="DE_SKR03_1200">Bank-Giro</msg>
<msg key="DE_SKR03_1400">Forderungen aus Lief. und Leist. Kundengruppe 0</msg>
<msg key="DE_SKR03_1540">Steuerüberzahlungen</msg>
<msg key="DE_SKR03_1542">Steuererstattungsansprüche gg. anderen EU-Ländern</msg>
<msg key="DE_SKR03_1545">Umsatzsteuerforderungen</msg>
<msg key="DE_SKR03_1548">Vorsteuer im Folgejahr abziehbar</msg>
<msg key="DE_SKR03_1570">Abziehbare Vorsteuer</msg>
<msg key="DE_SKR03_1571">Abziehbare Vorsteuer, 7%</msg>
<msg key="DE_SKR03_1575">Abziehbare Vorsteuer, 16%</msg>
<msg key="DE_SKR03_1576">Abziehbare Vorsteuer, 15%</msg>
<msg key="DE_SKR03_1577">Vorsteuer nach allg. Durchschnittssätzen UStVA KZ 63</msg>
<msg key="DE_SKR03_1775">Umsatzsteuer, 16%</msg>
<msg key="DE_SKR03_1776">Umsatzsteuer, 15%</msg>
<msg key="DE_SKR03_1780">Umsatzsteuer - Vorauszahlungen</msg>
<msg key="DE_SKR03_1781">Umsatzsteuer - Vorauszahlungen 1/11</msg>
<msg key="DE_SKR03_1782">Nachsteuer, UStVA KZ 65</msg>
<msg key="DE_SKR03_1789">Umsatzsteuer laufendes Jahr</msg>
<msg key="DE_SKR03_1790">Umsatzsteuer Vorjahr</msg>
<msg key="DE_SKR03_1791">Umsatzsteuer frühere Jahre</msg>
<msg key="DE_SKR03_1820">Sonderausg. beschr. abzugsf. (Privat Vollhaft./Einzelu.)</msg>
<msg key="DE_SKR03_1830">Sonderausg. unbeschr. abzugsf. (Privat Vollhaft./Einzelu.)</msg>
<msg key="DE_SKR03_1840">Privatspenden (Privat Vollhafter / Einzelunternehmer)</msg>
<msg key="DE_SKR03_1850">Außergewöhnliche Belastungen (Privat Vollhaft. / Einzelunt.)</msg>
<msg key="DE_SKR03_1890">Privateinlagen (Privat Vollhafter / Einzelunternehmer)</msg>
<msg key="DE_SKR03_2010">Betriebsfremde Aufw. (soweit nicht außerordentlich)</msg>
<msg key="DE_SKR03_2020">Periodenfremde Aufw. (soweit nicht außerordentlich)</msg>
<msg key="DE_SKR03_2100">Zinsen und ähnliche Aufwendungen</msg>
<msg key="DE_SKR03_2103">Steuerlich abzugsfähige, andere Nebenleistungen zu Steuern</msg>
<msg key="DE_SKR03_2104">Steuerlich nicht abzugsfähige, andere Nebenleistungen zu Steuern</msg>
<msg key="DE_SKR03_2107">Zinsaufwendungen §233a AO betriebliche Steuern</msg>
<msg key="DE_SKR03_2108">Zinsaufw. §233a, §234, §237 AO Personenst. §8 GewStG</msg>
<msg key="DE_SKR03_2109">Zinsaufwendungen an verbundene Unternehmen</msg>
<msg key="DE_SKR03_2110">Zinsaufwendungen für kurzfristige Verbindlichkeiten</msg>
<msg key="DE_SKR03_3410">Wareneingang, 16% Vorsteuer</msg>
<msg key="DE_SKR03_3736">Erhaltene Skonti, 16% Vorsteuer</msg>
<msg key="DE_SKR03_3740">Erhaltene Boni</msg>
<msg key="DE_SKR03_3750">Erhaltene Boni,   7% Vorsteuer</msg>
<msg key="DE_SKR03_3760">Erhaltene Boni, 15%+16% Vorsteuer</msg>
<msg key="DE_SKR03_3762">Erhaltene Boni, 16% Vorsteuer</msg>
<msg key="DE_SKR03_3764">Erhaltene Boni, 15% Vorsteuer</msg>
<msg key="DE_SKR03_3800">Anschaffungsnebenkosten</msg>
<msg key="DE_SKR03_3830">Leergut</msg>
<msg key="DE_SKR03_3850">Zölle und Einfuhrabgaben</msg>
<msg key="DE_SKR03_3960">Bestandsv. Roh-, Hilfs- u. Betriebsstoffe / bezogene Waren</msg>
<msg key="DE_SKR03_3970">Bestand Roh-, Hilfs- und Betriebsstoffe</msg>
<msg key="DE_SKR03_3980">Bestand Waren</msg>
<msg key="DE_SKR03_3990">Verrechnete Stoffkosten</msg>
<msg key="DE_SKR03_4000">Material- und Stoffverbrauch</msg>
<msg key="DE_SKR03_4100">Löhne und Gehälter</msg>
<msg key="DE_SKR03_4110">Löhne</msg>
<msg key="DE_SKR03_4120">Gehälter</msg>
<msg key="DE_SKR03_4124">Geschäftsführergehälter der GmbH-Gesellschafter</msg>
<msg key="DE_SKR03_4125">Ehegattengehalt</msg>
<msg key="DE_SKR03_4126">Tantiemen</msg>
<msg key="DE_SKR03_4127">Geschäftsführergehälter</msg>
<msg key="DE_SKR03_4128">Vergütungen an angestellte Mitunternehmer §15 EStG</msg>
<msg key="DE_SKR03_4130">Gesetzliche soziale Aufwendungen</msg>
<msg key="DE_SKR03_4137">Gesetzliche soziale Aufw. für Mitunternehmer §15 EStG</msg>
<msg key="DE_SKR03_4138">Beiträge zur Berufsgenossenschaft</msg>
<msg key="DE_SKR03_1360">Geldtransit Bank 1</msg>
<msg key="DE_SKR03_4140">Freiw. soziale Aufwendungen (lohnsteuerfrei)</msg>
<msg key="DE_SKR03_4145">Freiw. soziale Aufwendungen (lohnsteuerpflichtig)</msg>
<msg key="DE_SKR03_4149">Pauschale Lohnsteuer auf s. Bezüge (z.B. Fahrtkostenzuschuß)</msg>
<msg key="DE_SKR03_4150">Krankengeldzuschüsse</msg>
<msg key="DE_SKR03_4160">Versorgungskassen</msg>
<msg key="DE_SKR03_4165">Aufwendungen für die Altersversorgung</msg>
<msg key="DE_SKR03_4167">Pauschale Lohnsteuer auf s. Bezüge (z.B. Direktversicherung)</msg>
<msg key="DE_SKR03_4168">Aufw. f. die Altersversorgung f. Mitunternehmer §15 EStG</msg>
<msg key="DE_SKR03_4169">Aufwendungen für Unterstützung</msg>
<msg key="DE_SKR03_4170">Vermögenswirksame Leistungen</msg>
<msg key="DE_SKR03_4175">Fahrtkostenerstattung - Wohnung / Arbeitsstätte</msg>
<msg key="DE_SKR03_4180">Bedienungsgelder</msg>
<msg key="DE_SKR03_4190">Aushilfslöhne</msg>
<msg key="DE_SKR03_4199">Lohnsteuer für Aushilfen</msg>
<msg key="DE_SKR03_4200">Raumkosten</msg>
<msg key="DE_SKR03_4210">Miete</msg>
<msg key="DE_SKR03_4218">Gewerbesteuerlich zu berücks. Miete §8 GewStG</msg>
<msg key="DE_SKR03_4219">Vergütung an Mitu. f. mietw. Überl. v. Wirtschaftsg. §15EStG</msg>
<msg key="DE_SKR03_4220">Pacht</msg>
<msg key="DE_SKR03_4228">Gewerbesteuerlich zu berücks. Pacht §8 GewStG</msg>
<msg key="DE_SKR03_4229">Vergütung an Mitu. f. pachtw. Überl. v. Wirtschaftsg.§15EStG</msg>
<msg key="DE_SKR03_4230">Heizung</msg>
<msg key="DE_SKR03_4240">Gas, Strom, Wasser (Verwaltung, Vertrieb)</msg>
<msg key="DE_SKR03_4250">Reinigung</msg>
<msg key="DE_SKR03_4260">Instandhaltung betrieblicher Räume</msg>
<msg key="DE_SKR03_4270">Abgaben für betrieblich genutzten Grundbesitz</msg>
<msg key="DE_SKR03_4280">Sonstige Raumkosten</msg>
<msg key="DE_SKR03_4320">Gewerbesteuer (Vorauszahlung)</msg>
<msg key="DE_SKR03_4330">Gewerbeertragsteuer</msg>
<msg key="DE_SKR03_4335">Gewerbekapitalsteuer</msg>
<msg key="DE_SKR03_4340">Sonstige Betriebsteuern</msg>
<msg key="DE_SKR03_4350">Verbrauchsteuer</msg>
<msg key="DE_SKR03_4360">Versicherungen</msg>
<msg key="DE_SKR03_4380">Beiträge</msg>
<msg key="DE_SKR03_4390">Sonstige Abgaben</msg>
<msg key="DE_SKR03_4396">Steuerlich abzugsfähige Verspätungszuschläge und Zwangsgelder</msg>
<msg key="DE_SKR03_4397">Steuerlich nicht abzugsfähige Verspätungszuschläge und Zwangsgelder</msg>
<msg key="DE_SKR03_4400">Besondere Kosten (zur freien Verfügung)</msg>
<msg key="DE_SKR03_4500">Fahrzeugkosten</msg>
<msg key="DE_SKR03_4510">Kfz-Steuern</msg>
<msg key="DE_SKR03_4520">Kfz-Versicherungen</msg>
<msg key="DE_SKR03_4530">Laufende Kfz-Betriebskosten</msg>
<msg key="DE_SKR03_4540">Kfz-Reparaturen</msg>
<msg key="DE_SKR03_4550">Garagenmieten</msg>
<msg key="DE_SKR03_4570">Fremdfahrzeuge</msg>
<msg key="DE_SKR03_4580">Sonstige Kfz-Kosten</msg>
<msg key="DE_SKR03_4600">Werbe- und Reisekosten</msg>
<msg key="DE_SKR03_4610">Werbekosten</msg>
<msg key="DE_SKR03_4630">Geschenke bis DM 75,00</msg>
<msg key="DE_SKR03_4635">Geschenke über DM 75,00</msg>
<msg key="DE_SKR03_4638">Geschenke ausschließlich betrieblich genutzt</msg>
<msg key="DE_SKR03_4640">Repräsentationskosten</msg>
<msg key="DE_SKR03_4650">Bewirtungskosten</msg>
<msg key="DE_SKR03_4653">Aufwerksamkeiten</msg>
<msg key="DE_SKR03_4654">Nicht abzugsfähige Bewirtungskosten</msg>
<msg key="DE_SKR03_4655">Nicht abzugsfähige Betriebsausgaben</msg>
<msg key="DE_SKR03_4660">Reisekosten Arbeitnehmer</msg>
<msg key="DE_SKR03_4666">Reisekost. Arbeitn., 12,3%/13,1% VSt  Verpfl.Mehr- / Übern.Aufw.</msg>
<msg key="DE_SKR03_4667">Reisekost. Arbeitn., 9,8%/10,5% VSt Gesamtpauschal.</msg>
<msg key="DE_SKR03_4670">Reisekosten Unternehmer</msg>
<msg key="DE_SKR03_4675">Reisekosten Unternehmer, 9,8/10,5% VSt sonst.Gesamtpauschal.</msg>
<msg key="DE_SKR03_4676">Reisekost. Untern., 12,3%/13,1% VSt Verpfl.Mehr- / Übern.Aufw.</msg>
<msg key="DE_SKR03_4677">Reisekosten Unternehmer, 9,8%/10,5% VSt Verpfl.Mehraufw. Gesamtpauschal.</msg>
<msg key="DE_SKR03_4678">Km-Geld Erstattung, Unternehmer, 5,7%/6,1% VSt</msg>
<msg key="DE_SKR03_4685">Km-Geld-Erstattung, Arbeitnehmer  8,2%/8,7% VSt</msg>
<msg key="DE_SKR03_4700">Kosten der Warenabgabe</msg>
<msg key="DE_SKR03_4710">Verpackungsmaterial</msg>
<msg key="DE_SKR03_4730">Ausgangsfrachten</msg>
<msg key="DE_SKR03_4750">Transportversicherungen</msg>
<msg key="DE_SKR03_4760">Verkaufsprovisionen</msg>
<msg key="DE_SKR03_4780">Fremdarbeiten</msg>
<msg key="DE_SKR03_4790">Aufwand für Gewährleistungen</msg>
<msg key="DE_SKR03_4800">Reparat. u. Inst. v. Maschinen u. technischen Anlagen</msg>
<msg key="DE_SKR03_4805">Reparat. u. Inst. v. and. Anl. d. Betr.- u. Geschäftsausst.</msg>
<msg key="DE_SKR03_4809">Sonstige Reparaturen und Instandhaltungen</msg>
<msg key="DE_SKR03_4810">Mietleasing</msg>
<msg key="DE_SKR03_4815">Kaufleasing</msg>
<msg key="DE_SKR03_4820">Abschr. a. Aufw. f.d. Ingangs. u. Erw. des Geschäftsbetr.</msg>
<msg key="DE_SKR03_4822">Abschr. a. immaterielle Vermögensgegenstände</msg>
<msg key="DE_SKR03_4824">Abschreibung auf den Geschäfts- oder Firmenwert</msg>
<msg key="DE_SKR03_4826">Außerplanm. Abschr. a. immaterielle Vermögensgegenstände</msg>
<msg key="DE_SKR03_4830">Abschreibungen auf Sachanlagen</msg>
<msg key="DE_SKR03_4840">Außerplanm. Abschreibungen auf Sachanlagen</msg>
<msg key="DE_SKR03_4850">Abschr. a. Sachanl. aufgrund steuerl. Sondervorschriften</msg>
<msg key="DE_SKR03_4855">Sofortabschreibung geringwertiger Wirtschaftsgüter</msg>
<msg key="DE_SKR03_4860">Abschreibung auf aktivierte, geringwertige Wirtschaftsgüter</msg>
<msg key="DE_SKR03_4865">Außerplanmäßige Abschr. a. aktivierte GWG</msg>
<msg key="DE_SKR03_4870">Abschreibungen auf Finanzanlagen</msg>
<msg key="DE_SKR03_4872">Abschr. aufgrund v. Verlustant. an Mitunt. §8 GewStG</msg>
<msg key="DE_SKR03_4874">Abschr. a. Finanzanl. aufgrund steuerl. Sondervorschriften</msg>
<msg key="DE_SKR03_4875">Abschreibungen auf Wertpapiere des Umlaufvermögens</msg>
<msg key="DE_SKR03_4880">Abschr. a. Umlaufv. ohne Wertpapiere (soweit unübl. Höhe)</msg>
<msg key="DE_SKR03_4882">Abschr. a. Umlaufv. steuerrechtl. bedingt (unübl. Höhe)</msg>
<msg key="DE_SKR03_4887">Abschr. a. Umlaufv., steuerrechtlich bedingt (übl. Höhe)</msg>
<msg key="DE_SKR03_4890">Vorwegn. künftiger Wertschw. im Umlaufv. (unübl. Höhe)</msg>
<msg key="DE_SKR03_4900">Sonstige betriebliche Aufwendungen</msg>
<msg key="DE_SKR03_4905">Sonstige Aufwendungen betrieblich und regelmäßig</msg>
<msg key="DE_SKR03_4910">Porto</msg>
<msg key="DE_SKR03_4920">Telefon</msg>
<msg key="DE_SKR03_4925">Telefax, Fernschreiber</msg>
<msg key="DE_SKR03_4930">Bürobedarf</msg>
<msg key="DE_SKR03_4940">Zeitschriften, Bücher</msg>
<msg key="DE_SKR03_4945">Fortbildungskosten</msg>
<msg key="DE_SKR03_4946">Freiwillige Sozialleistungen</msg>
<msg key="DE_SKR03_4948">Vergütungen an freiberufliche Mitunternehmer §15 EStG</msg>
<msg key="DE_SKR03_4950">Rechts- und Beratungskosten</msg>
<msg key="DE_SKR03_4955">Buchführungskosten</msg>
<msg key="DE_SKR03_4957">Abschluß- und Prüfungskosten</msg>
<msg key="DE_SKR03_4960">Mieten für Einrichtungen</msg>
<msg key="DE_SKR03_4968">Gewerbest. zu berücks. Miete f. Einrichtungen §8 GewStG</msg>
<msg key="DE_SKR03_4969">Aufwendungen für Abraum- und Abfallbeseitigung</msg>
<msg key="DE_SKR03_4970">Nebenkosten des Geldverkehrs</msg>
<msg key="DE_SKR03_4980">Betriebsbedarf</msg>
<msg key="DE_SKR03_4985">Werkzeuge und Kleingeräte</msg>
<msg key="DE_SKR03_4996">Herstellungskosten</msg>
<msg key="DE_SKR03_4997">Verwaltungskosten</msg>
<msg key="DE_SKR03_4998">Vertriebskosten</msg>
<msg key="DE_SKR03_4999">Gegenkonto 49960-49980</msg>
<msg key="DE_SKR03_7140">Fertige Waren (Bestand)</msg>
<msg key="DE_SKR03_8100">Steuerfreie Umsätze o. VSt-Abzug §4 Nr.8 ff. UStG</msg>
<msg key="DE_SKR03_8500">Provisionserlöse</msg>
<msg key="DE_SKR03_8504">Provisionserlöse steuerfrei (§4 Nr.8ff UStG)</msg>
<msg key="DE_SKR03_8505">Provisionserlöse steuerfrei (§4 Nr.5 UStG)</msg>
<msg key="DE_SKR03_8506">Provisionserlöse,  7% USt</msg>
<msg key="DE_SKR03_8507">Provisionserlöse, 15% Ust</msg>
<msg key="DE_SKR03_8508">Provisionserlöse, 15%/16% USt</msg>
<msg key="DE_SKR03_8509">Provisionserlöse, 16% Ust</msg>
<msg key="DE_SKR03_8591">Sachbezüge,   7% USt (Waren)</msg>
<msg key="DE_SKR03_8595">Sachbezüge, 15%/16% USt (Waren)</msg>
<msg key="DE_SKR03_8596">Sachbezüge, 16% USt (Waren)</msg>
<msg key="DE_SKR03_8597">Sachbezüge, 15% USt (Waren)</msg>
<msg key="DE_SKR03_8630">Sonstige Erlöse betrieblich und regelmäßig, 7% USt</msg>
<msg key="DE_SKR03_8645">Sonstige Erlöse betrieblich und regelmäßig, 16% Ust</msg>
<msg key="DE_SKR03_8730">Gewährte Skonti</msg>
<msg key="DE_SKR03_8731">Gewährte Skonti,  7% USt</msg>
<msg key="DE_SKR03_8735">Gewährte Skonti, 16% Ust</msg>
<msg key="DE_SKR03_8740">Gewährte Boni</msg>
<msg key="DE_SKR03_8750">Gewährte Boni,  7% USt</msg>
<msg key="DE_SKR03_8762">Gewährte Boni, 16% Ust</msg>
<msg key="DE_SKR03_8770">Gewährte Rabatte</msg>
<msg key="DE_SKR03_8780">Gewährte Rabatte,  7% USt</msg>
<msg key="DE_SKR03_8792">Gewährte Rabatte, 16% Ust</msg>
<msg key="DE_SKR03_8800">Erlöse aus Anlagenverkäufen</msg>
<msg key="DE_SKR03_8801">Erlöse aus Anlagenverkäufen 15%/16% USt (bei Buchverlust)</msg>
<msg key="DE_SKR03_8810">Erlöse aus Anlagenverkäufen 16% USt (bei Buchverlust)</msg>
<msg key="DE_SKR03_8815">Erlöse aus Anlagenverkäufen 15% USt (bei Buchverlust)</msg>
<msg key="DE_SKR03_8820">Erlöse aus Anlagenverkäufen 15%/16% USt (bei Buchgewinn)</msg>
<msg key="DE_SKR03_8829">Erlöse aus Anlagenverkäufen (bei Buchgewinn)</msg>
<msg key="DE_SKR03_8830">Erlöse aus Anlagenverkäufen 16% USt (bei Buchgewinn)</msg>
<msg key="DE_SKR03_8835">Erlöse aus Anlagenverkäufen 15% USt (bei Buchgewinn)</msg>
<msg key="DE_SKR03_8900">Eigenverbrauch</msg>
<msg key="DE_SKR03_8905">Entnahme Gegenstände ohne USt</msg>
<msg key="DE_SKR03_8908">Entnahme von Gegenstände, 16% USt §1 Abs.1 Nr.2a UStG</msg>
<msg key="DE_SKR03_8909">Entnahme von Gegenstände, 15% USt §1 Abs.1 Nr.2a UStG</msg>
<msg key="DE_SKR03_8910">Entnahme von Gegenstände, 15%/16% USt §1 Abs.1 Nr.2a UStG</msg>
<msg key="DE_SKR03_8915">Entnahme von Gegenstände, 7% USt §1 Abs.1 Nr.2a UStG</msg>
<msg key="DE_SKR03_8920">Entnahme v. sonst. Leist., 15%/16% USt §1 A.1 Nr.2b UStG</msg>
<msg key="DE_SKR03_8930">Entnahme v. sonst. Leist., 7% USt §1 A.1 Nr.2b UStG</msg>
<msg key="DE_SKR03_8937">Entnahme v. sonst. Leist., 16% USt §1 A.1 Nr.2b UStG</msg>
<msg key="DE_SKR03_8938">Entnahme v. sonst. Leist., 15% USt §1 A.1 Nr.2b UStG</msg>
<msg key="DE_SKR03_8939">Entnahme v. sonst. Leist., ohne USt §1 A.1 Nr.2b UStG</msg>
<msg key="DE_SKR03_8941">Eigenverbr., 7% Ust §4 A.1 Nr.5 1-7, A.7 EStG</msg>
<msg key="DE_SKR03_8942">Eigenverbr., 16% Ust  §4 A.1 Nr.5 1-7, A.7 EStG</msg>
<msg key="DE_SKR03_8944">Eigenverbr., ohne Ust §4 A.1 Nr.5 1-7, A.7 EStG</msg>
<msg key="DE_SKR03_8950">Nicht steuerbare Umsätze</msg>
<msg key="DE_SKR03_8955">Umsatzsteuervergütungen</msg>
<msg key="DE_SKR03_8960">Bestandsveränd. - unfertige Erzeugnisse</msg>
<msg key="DE_SKR03_8970">Bestandsveränd. - unfertige Leistungen</msg>
<msg key="DE_SKR03_8975">Bestandsveränd. - in Ausführung befindliche Bauaufträge</msg>
<msg key="DE_SKR03_8977">Bestandsveränd. - in Arbeit befindliche Aufträge</msg>
<msg key="DE_SKR03_8980">Bestandsveränd. - fertige Erzeugnisse</msg>
<msg key="DE_SKR03_8990">Bestandsveränd. - andere aktivierte Eigenleistungen</msg>
<msg key="DE_SKR03_9000">Saldenvorträge Sachkonten</msg>
<msg key="DE_SKR03_9008">Saldenvorträge Debitoren</msg>
<msg key="DE_SKR03_9009">Saldenvorträge Kreditoren</msg>
<msg key="DE_SKR03_9100">Saldovortragskonto der Statistikkonten</msg>
<msg key="DE_SKR03_1800">Privatentn. allg. (Privat Vollhafter / Einzelunternehmer)</msg>
<msg key="DE_SKR03_2000">Außerordentliche Aufwendungen</msg>
<msg key="DE_SKR03_1600">Verb. aus Lief. und Leist. Lieferantengruppe 0</msg>
<msg key="DE_SKR03_3400">Wareneingang, 16% Vorsteuer</msg>
<msg key="DE_SKR03_8400">Umsatzerlöse 16%</msg>
<msg key="DE_SKR03_8840">Erträge aus Kursdifferenzen</msg>
<msg key="0">Null</msg>
<msg key="1">ein</msg>
<msg key="2">zwei</msg>
<msg key="3">drei</msg>
<msg key="4">vier</msg>
<msg key="5">fünf</msg>
<msg key="6">sechs</msg>
<msg key="7">sieben</msg>
<msg key="8">acht</msg>
<msg key="9">neun</msg>
<msg key="10">zehn</msg>
<msg key="11">elf</msg>
<msg key="12">zwölf</msg>
<msg key="13">dreizehn</msg>
<msg key="14">vierzehn</msg>
<msg key="15">fünfzehn</msg>
<msg key="16">sechzehn</msg>
<msg key="17">siebzehn</msg>
<msg key="18">achtzehn</msg>
<msg key="19">neunzehn</msg>
<msg key="20">zwanzig</msg>
<msg key="30">dreissig</msg>
<msg key="40">vierzig</msg>
<msg key="50">fünfzig</msg>
<msg key="60">sechzig</msg>
<msg key="70">siebzig</msg>
<msg key="80">achtzig</msg>
<msg key="90">neunzig</msg>
<msg key="10__2">hundert</msg>
<msg key="10__3">tausend</msg>
<msg key="10__6">million</msg>
<msg key="10__9">milliarde</msg>
<msg key="10__12">billion</msg>
</message_catalog>
